{
  "swagger": "2.0",
  "info": {
    "title": "Auth Service API",
    "version": "1.0"
  },
  "tags": [
    {
      "name": "AuthService"
    }
  ],
  "consumes": [
    "application/json"
  ],
  "produces": [
    "application/json"
  ],
  "paths": {
    "/v1/auth/forgot-password": {
      "post": {
        "summary": "Forgot password",
        "description": "Request a password reset link sent to the user email",
        "operationId": "AuthService_ForgotPassword",
        "responses": {
          "200": {
            "description": "A successful response.",
            "schema": {
              "$ref": "#/definitions/pbForgotPasswordResponse"
            }
          },
          "default": {
            "description": "An unexpected error response.",
            "schema": {
              "$ref": "#/definitions/rpcStatus"
            }
          }
        },
        "parameters": [
          {
            "name": "body",
            "in": "body",
            "required": true,
            "schema": {
              "$ref": "#/definitions/pbForgotPasswordRequest"
            }
          }
        ],
        "tags": [
          "auth"
        ]
      }
    },
    "/v1/auth/login": {
      "post": {
        "summary": "Login user",
        "description": "Login and receive access + refresh tokens",
        "operationId": "AuthService_LoginUser",
        "responses": {
          "200": {
            "description": "A successful response.",
            "schema": {
              "$ref": "#/definitions/pbLoginUserResponse"
            }
          },
          "default": {
            "description": "An unexpected error response.",
            "schema": {
              "$ref": "#/definitions/rpcStatus"
            }
          }
        },
        "parameters": [
          {
            "name": "body",
            "in": "body",
            "required": true,
            "schema": {
              "$ref": "#/definitions/pbLoginUserRequest"
            }
          }
        ],
        "tags": [
          "auth"
        ]
      }
    },
    "/v1/auth/logout": {
      "post": {
        "summary": "Logout",
        "description": "Revoke the refresh token and end the session",
        "operationId": "AuthService_Logout",
        "responses": {
          "200": {
            "description": "A successful response.",
            "schema": {
              "$ref": "#/definitions/pbLogoutResponse"
            }
          },
          "default": {
            "description": "An unexpected error response.",
            "schema": {
              "$ref": "#/definitions/rpcStatus"
            }
          }
        },
        "parameters": [
          {
            "name": "body",
            "in": "body",
            "required": true,
            "schema": {
              "$ref": "#/definitions/pbLogoutRequest"
            }
          }
        ],
        "tags": [
          "auth"
        ]
      }
    },
    "/v1/auth/refresh": {
      "post": {
        "summary": "Refresh access token",
        "description": "Use a refresh token to obtain a new access token",
        "operationId": "AuthService_RefreshToken",
        "responses": {
          "200": {
            "description": "A successful response.",
            "schema": {
              "$ref": "#/definitions/pbRefreshTokenResponse"
            }
          },
          "default": {
            "description": "An unexpected error response.",
            "schema": {
              "$ref": "#/definitions/rpcStatus"
            }
          }
        },
        "parameters": [
          {
            "name": "body",
            "in": "body",
            "required": true,
            "schema": {
              "$ref": "#/definitions/pbRefreshTokenRequest"
            }
          }
        ],
        "tags": [
          "auth"
        ]
      }
    },
    "/v1/auth/register": {
      "post": {
        "summary": "Register user",
        "description": "Register a new user account",
        "operationId": "AuthService_RegisterUser",
        "responses": {
          "200": {
            "description": "A successful response.",
            "schema": {
              "$ref": "#/definitions/pbRegisterUserResponse"
            }
          },
          "default": {
            "description": "An unexpected error response.",
            "schema": {
              "$ref": "#/definitions/rpcStatus"
            }
          }
        },
        "parameters": [
          {
            "name": "body",
            "in": "body",
            "required": true,
            "schema": {
              "$ref": "#/definitions/pbRegisterUserRequest"
            }
          }
        ],
        "tags": [
          "auth"
        ]
      }
    },
    "/v1/auth/resend-verification": {
      "post": {
        "summary": "Resend verification email",
        "description": "Resend the email verification link",
        "operationId": "AuthService_ResendVerification",
        "responses": {
          "200": {
            "description": "A successful response.",
            "schema": {
              "$ref": "#/definitions/pbResendVerificationResponse"
            }
          },
          "default": {
            "description": "An unexpected error response.",
            "schema": {
              "$ref": "#/definitions/rpcStatus"
            }
          }
        },
        "parameters": [
          {
            "name": "body",
            "in": "body",
            "required": true,
            "schema": {
              "$ref": "#/definitions/pbResendVerificationRequest"
            }
          }
        ],
        "tags": [
          "auth"
        ]
      }
    },
    "/v1/auth/reset-password": {
      "post": {
        "summary": "Reset password",
        "description": "Reset the user password using the token from the reset email",
        "operationId": "AuthService_ResetPassword",
        "responses": {
          "200": {
            "description": "A successful response.",
            "schema": {
              "$ref": "#/definitions/pbResetPasswordResponse"
            }
          },
          "default": {
            "description": "An unexpected error response.",
            "schema": {
              "$ref": "#/definitions/rpcStatus"
            }
          }
        },
        "parameters": [
          {
            "name": "body",
            "in": "body",
            "required": true,
            "schema": {
              "$ref": "#/definitions/pbResetPasswordRequest"
            }
          }
        ],
        "tags": [
          "auth"
        ]
      }
    },
    "/v1/auth/verify-email": {
      "post": {
        "summary": "Verify email",
        "description": "Verify a user email address using the token sent via email",
        "operationId": "AuthService_VerifyEmail",
        "responses": {
          "200": {
            "description": "A successful response.",
            "schema": {
              "$ref": "#/definitions/pbVerifyEmailResponse"
            }
          },
          "default": {
            "description": "An unexpected error response.",
            "schema": {
              "$ref": "#/definitions/rpcStatus"
            }
          }
        },
        "parameters": [
          {
            "name": "body",
            "in": "body",
            "required": true,
            "schema": {
              "$ref": "#/definitions/pbVerifyEmailRequest"
            }
          }
        ],
        "tags": [
          "auth"
        ]
      }
    },
    "/v1/users/me": {
      "get": {
        "summary": "Get current user",
        "description": "Get the authenticated user's profile",
        "operationId": "AuthService_GetUser",
        "responses": {
          "200": {
            "description": "A successful response.",
            "schema": {
              "$ref": "#/definitions/pbGetUserResponse"
            }
          },
          "default": {
            "description": "An unexpected error response.",
            "schema": {
              "$ref": "#/definitions/rpcStatus"
            }
          }
        },
        "tags": [
          "users"
        ],
        "security": [
          {
            "BearerAuth": []
          }
        ]
      },
      "patch": {
        "summary": "Update current user",
        "description": "Update the authenticated user's profile",
        "operationId": "AuthService_UpdateUser",
        "responses": {
          "200": {
            "description": "A successful response.",
            "schema": {
              "$ref": "#/definitions/pbUpdateUserResponse"
            }
          },
          "default": {
            "description": "An unexpected error response.",
            "schema": {
              "$ref": "#/definitions/rpcStatus"
            }
          }
        },
        "parameters": [
          {
            "name": "body",
            "in": "body",
            "required": true,
            "schema": {
              "$ref": "#/definitions/pbUpdateUserRequest"
            }
          }
        ],
        "tags": [
          "users"
        ],
        "security": [
          {
            "BearerAuth": []
          }
        ]
      }
    },
    "/v1/users/me/password": {
      "patch": {
        "summary": "Change password",
        "description": "Change the authenticated user's password",
        "operationId": "AuthService_ChangePassword",
        "responses": {
          "200": {
            "description": "A successful response.",
            "schema": {
              "$ref": "#/definitions/pbChangePasswordResponse"
            }
          },
          "default": {
            "description": "An unexpected error response.",
            "schema": {
              "$ref": "#/definitions/rpcStatus"
            }
          }
        },
        "parameters": [
          {
            "name": "body",
            "in": "body",
            "required": true,
            "schema": {
              "$ref": "#/definitions/pbChangePasswordRequest"
            }
          }
        ],
        "tags": [
          "users"
        ],
        "security": [
          {
            "BearerAuth": []
          }
        ]
      }
    }
  },
  "definitions": {
    "pbChangePasswordRequest": {
      "type": "object",
      "properties": {
        "oldPassword": {
          "type": "string"
        },
        "newPassword": {
          "type": "string"
        }
      }
    },
    "pbChangePasswordResponse": {
      "type": "object"
    },
    "pbForgotPasswordRequest": {
      "type": "object",
      "properties": {
        "email": {
          "type": "string"
        }
      }
    },
    "pbForgotPasswordResponse": {
      "type": "object",
      "properties": {
        "message": {
          "type": "string"
        }
      }
    },
    "pbGetUserResponse": {
      "type": "object",
      "properties": {
        "user": {
          "$ref": "#/definitions/pbUser"
        }
      }
    },
    "pbLoginUserRequest": {
      "type": "object",
      "properties": {
        "email": {
          "type": "string"
        },
        "password": {
          "type": "string"
        }
      }
    },
    "pbLoginUserResponse": {
      "type": "object",
      "properties": {
        "tokenId": {
          "type": "string"
        },
        "accessToken": {
          "type": "string"
        },
        "accessTokenExpiresAt": {
          "type": "string",
          "format": "date-time"
        },
        "refreshToken": {
          "type": "string"
        },
        "refreshTokenExpiresAt": {
          "type": "string",
          "format": "date-time"
        },
        "user": {
          "$ref": "#/definitions/pbUser"
        }
      }
    },
    "pbLogoutRequest": {
      "type": "object",
      "properties": {
        "refreshToken": {
          "type": "string"
        }
      }
    },
    "pbLogoutResponse": {
      "type": "object"
    },
    "pbRefreshTokenRequest": {
      "type": "object",
      "properties": {
        "refreshToken": {
          "type": "string"
        }
      }
    },
    "pbRefreshTokenResponse": {
      "type": "object",
      "properties": {
        "accessToken": {
          "type": "string"
        },
        "accessTokenExpiresAt": {
          "type": "string",
          "format": "date-time"
        }
      }
    },
    "pbRegisterUserRequest": {
      "type": "object",
      "properties": {
        "username": {
          "type": "string"
        },
        "email": {
          "type": "string"
        },
        "password": {
          "type": "string"
        },
        "fullName": {
          "type": "string"
        }
      }
    },
    "pbRegisterUserResponse": {
      "type": "object",
      "properties": {
        "user": {
          "$ref": "#/definitions/pbUser"
        }
      }
    },
    "pbResendVerificationRequest": {
      "type": "object",
      "properties": {
        "email": {
          "type": "string"
        }
      }
    },
    "pbResendVerificationResponse": {
      "type": "object",
      "properties": {
        "message": {
          "type": "string"
        }
      }
    },
    "pbResetPasswordRequest": {
      "type": "object",
      "properties": {
        "token": {
          "type": "string"
        },
        "newPassword": {
          "type": "string"
        }
      }
    },
    "pbResetPasswordResponse": {
      "type": "object",
      "properties": {
        "message": {
          "type": "string"
        }
      }
    },
    "pbUpdateUserRequest": {
      "type": "object",
      "properties": {
        "fullName": {
          "type": "string"
        },
        "avatarUrl": {
          "type": "string"
        }
      }
    },
    "pbUpdateUserResponse": {
      "type": "object",
      "properties": {
        "user": {
          "$ref": "#/definitions/pbUser"
        }
      }
    },
    "pbUser": {
      "type": "object",
      "properties": {
        "userId": {
          "type": "string"
        },
        "username": {
          "type": "string"
        },
        "email": {
          "type": "string"
        },
        "fullName": {
          "type": "string"
        },
        "avatarUrl": {
          "type": "string"
        },
        "role": {
          "type": "string"
        },
        "emailVerified": {
          "type": "boolean"
        },
        "createdAt": {
          "type": "string",
          "format": "date-time"
        }
      }
    },
    "pbVerifyEmailRequest": {
      "type": "object",
      "properties": {
        "token": {
          "type": "string"
        }
      }
    },
    "pbVerifyEmailResponse": {
      "type": "object",
      "properties": {
        "message": {
          "type": "string"
        }
      }
    },
    "protobufAny": {
      "type": "object",
      "properties": {
        "@type": {
          "type": "string"
        }
      },
      "additionalProperties": {}
    },
    "rpcStatus": {
      "type": "object",
      "properties": {
        "code": {
          "type": "integer",
          "format": "int32"
        },
        "message": {
          "type": "string"
        },
        "details": {
          "type": "array",
          "items": {
            "type": "object",
            "$ref": "#/definitions/protobufAny"
          }
        }
      }
    }
  },
  "securityDefinitions": {
    "BearerAuth": {
      "type": "apiKey",
      "name": "Authorization",
      "in": "header"
    }
  }
}
